{"info": "操作完成", "code": "200", "data": [{"goods_cate_name": "冬上新", "goods_name": "卫衣女2018新款宽松连帽衫韩版大码保暖长袖秋冬加绒加厚外套上衣", "goods_image": "//g-search3.alicdn.com/img/bao/uploaded/i4/i3/3322280483/O1CN011FRFlUTsexQQYCC_!!0-item_pic.jpg", "goods_detail_url": "https://detail.tmall.com/item.htm?id=574126442710&ns=1&abbucket=8", "goods_product_id": "574126442710", "goods_price": "89.00", "goods_sale_num": 7243, "shop_name": "常暖旗舰店", "platform": 1, "goods_total_score": "4.9", "goods_comment_num": 13940}, {"goods_cate_name": "半身裙", "goods_name": "针织半身裙女秋冬2018新款毛线中长款包臀修身开叉黑色高腰长裙", "goods_image": "//g-search1.alicdn.com/img/bao/uploaded/i4/i4/3595919503/O1CN01KPF9OK2K4QHosBZLt_!!0-item_pic.jpg", "goods_detail_url": "https://detail.tmall.com/item.htm?id=576425060153&ns=1&abbucket=8", "goods_product_id": "576425060153", "goods_price": "99.00", "goods_sale_num": 6179, "shop_name": "蔻兰芷旗舰店", "platform": 1, "goods_total_score": "4.9", "goods_comment_num": 2294}, {"goods_cate_name": "半身裙", "goods_name": "毛呢格子百褶a字裙女2018秋冬新款高腰ins超火的半身裙子短裙冬裙", "goods_image": "//g-search3.alicdn.com/img/bao/uploaded/i4/i1/1625267564/O1CN01dFV4cI25kMJVUuDop_!!0-item_pic.jpg", "goods_detail_url": "https://detail.tmall.com/item.htm?id=558817511094&ns=1&abbucket=8", "goods_product_id": "558817511094", "goods_price": "39.00", "goods_sale_num": 6179, "shop_name": "吾子其旗舰店", "platform": 1, "goods_total_score": "4.8", "goods_comment_num": 25184}, {"goods_cate_name": "卫衣绒衫", "goods_name": "卫衣2018新款长袖韩版宽松秋冬ins超火女上衣连帽加绒加厚百搭潮", "goods_image": "//g-search3.alicdn.com/img/bao/uploaded/i4/i1/3098206259/O1CN011w6fRcBZwlqRAB5_!!0-item_pic.jpg", "goods_detail_url": "https://detail.tmall.com/item.htm?id=577790725994&ns=1&abbucket=8", "goods_product_id": "577790725994", "goods_price": "79.00", "goods_sale_num": 7991, "shop_name": "格贝慕旗舰店", "platform": 1, "goods_total_score": "4.9", "goods_comment_num": 7495}, {"goods_cate_name": "卫衣绒衫", "goods_name": "卫衣2018新款女加厚加绒秋冬厚款中长款长袖韩版宽松连帽打底外套", "goods_image": "//g-search2.alicdn.com/img/bao/uploaded/i4/i4/3257266135/O1CN011vBsKNl1SzmjHSp_!!0-item_pic.jpg", "goods_detail_url": "https://detail.tmall.com/item.htm?id=579020658117&ns=1&abbucket=8", "goods_product_id": "579020658117", "goods_price": "168.00", "goods_sale_num": 2173, "shop_name": "红粉搭档旗舰店", "platform": 1, "goods_total_score": "4.9", "goods_comment_num": 1158}, {"goods_cate_name": "毛针织衫", "goods_name": "秋冬男士高领毛衣韩版修身纯色针织衫翻领加厚套头打底衫男线衣潮", "goods_image": "//g-search3.alicdn.com/img/bao/uploaded/i4/i3/1776477331/O1CN01YSgh41241e215A0CG_!!1776477331.jpg", "goods_detail_url": "https://detail.tmall.com/item.htm?id=524466038668&ns=1&abbucket=8", "goods_product_id": "524466038668", "goods_price": "69.00", "goods_sale_num": 17139, "shop_name": "tkz旗舰店", "platform": 1, "goods_total_score": "4.8", "goods_comment_num": 48114}, {"goods_cate_name": "毛针织衫", "goods_name": "毛衣男圆领针织衫秋季2018新款韩版潮流男生毛线冬季线衣毛衫秋装", "goods_image": "//g-search1.alicdn.com/img/bao/uploaded/i4/i4/3055237276/TB1Tb2tmMHqK1RjSZFgXXa7JXXa_!!0-item_pic.jpg", "goods_detail_url": "https://detail.tmall.com/item.htm?id=578219713325&ns=1&abbucket=8", "goods_product_id": "578219713325", "goods_price": "98.00", "goods_sale_num": 8748, "shop_name": "vuug旗舰店", "platform": 1, "goods_total_score": "4.9", "goods_comment_num": 3952}, {"goods_cate_name": "毛针织衫", "goods_name": "恒源祥男士羊毛衫圆领秋冬款韩版薄款毛衣男中年打底衫套头针织衫", "goods_image": "//g-search1.alicdn.com/img/bao/uploaded/i4/i2/2252952469/O1CN011U6qMAwQ0sSZtzR_!!0-item_pic.jpg", "goods_detail_url": "https://detail.tmall.com/item.htm?id=578283544117&ns=1&abbucket=8", "goods_product_id": "578283544117", "goods_price": "298.00", "goods_sale_num": 2490, "shop_name": "中耐男装专营店", "platform": 1, "goods_total_score": "4.8", "goods_comment_num": 769}, {"goods_cate_name": "Top神店", "goods_name": "一位无足轻重的神 Sergio Top 文学 外国科幻,侦探小说 外国小说 新华书店正版图书籍上海人民出版社", "goods_image": "//g-search3.alicdn.com/img/bao/uploaded/i4/i3/2872857296/TB1Ul1KmVzqK1RjSZFCXXbbxVXa_!!0-item_pic.jpg", "goods_detail_url": "https://detail.tmall.com/item.htm?id=537547931028&ns=1&abbucket=8", "goods_product_id": "537547931028", "goods_price": "28.30", "goods_sale_num": 0, "shop_name": "博采雅集图书专营店", "platform": 2, "goods_total_score": "4.9", "goods_comment_num": 0}, {"goods_cate_name": "羽绒服", "goods_name": "波司登羽绒服女中长款 新款大毛领户外工装加厚鹅绒外套B80142148", "goods_image": "//g-search3.alicdn.com/img/bao/uploaded/i4/i2/1746350566/O1CN01M63mCs1G3Ge3tFrl5_!!1746350566.jpg", "goods_detail_url": "https://detail.tmall.com/item.htm?id=577366413296&ns=1&abbucket=8", "goods_product_id": "577366413296", "goods_price": "2698.00", "goods_sale_num": 209, "shop_name": "波司登乐淘专卖店", "platform": 1, "goods_total_score": "4.9", "goods_comment_num": 51}, {"goods_cate_name": "Top神店", "goods_name": "★TOP漫畫城★神存在的洋果子店(1-7END)全新現貨-若木民喜", "goods_image": "//g-search1.alicdn.com/img/bao/uploaded/i4/i3/1042705759/TB2nLpifSFmpuFjSZFrXXayOXXa_!!1042705759.jpg", "goods_detail_url": "https://item.taobao.com/item.htm?id=545338394285&ns=1&abbucket=8#detail", "goods_product_id": "545338394285", "goods_price": "209.30", "goods_sale_num": 0, "shop_name": "top漫画城", "platform": 2, "goods_total_score": "4.9", "goods_comment_num": 0}]}
{"info": "操作完成", "code": "200", "data": [{"goods_cate_name": "羽绒服", "goods_name": "波司登羽绒服女 新款鹅绒加厚中长款过膝修身大毛领冬装B80142154", "goods_image": "//g-search3.alicdn.com/img/bao/uploaded/i4/i1/1746350566/O1CN01VzFq5d1G3GeDCPGe6_!!0-item_pic.jpg", "goods_detail_url": "https://detail.tmall.com/item.htm?id=577472190357&ns=1&abbucket=8", "goods_product_id": "577472190357", "goods_price": "2499.00", "goods_sale_num": 241, "shop_name": "波司登乐淘专卖店", "platform": 1, "goods_total_score": "4.9", "goods_comment_num": 88}, {"goods_cate_name": "棉衣棉服", "goods_name": "棉衣男士冬季外套加厚短款韩版潮流羽绒棉服学生2018新款冬装袄子", "goods_image": "//g-search3.alicdn.com/img/bao/uploaded/i4/i1/2981527120/O1CN0122T0SB9YB7QtMUm_!!0-item_pic.jpg", "goods_detail_url": "https://detail.tmall.com/item.htm?id=578971948089&ns=1&abbucket=8", "goods_product_id": "578971948089", "goods_price": "268.00", "goods_sale_num": 2650, "shop_name": "俊霸王子旗舰店", "platform": 1, "goods_total_score": "4.9", "goods_comment_num": 1529}, {"goods_cate_name": "棉衣棉服", "goods_name": "棉衣男中长款2018新款冬装加绒加厚中年棉袄子男棉服冬季男士外套", "goods_image": "//g-search3.alicdn.com/img/bao/uploaded/i4/i1/2218691669/O1CN01ZcuMFN1OCRVR9pcuI_!!2218691669.jpg", "goods_detail_url": "https://detail.tmall.com/item.htm?id=561413753503&ns=1&abbucket=8", "goods_product_id": "561413753503", "goods_price": "298.00", "goods_sale_num": 2666, "shop_name": "裂谷服饰专营店", "platform": 1, "goods_total_score": "4.9", "goods_comment_num": 7234}, {"goods_cate_name": "棉衣棉服", "goods_name": "冬季加厚款带帽中长款中老年人男装棉衣爸爸冬装羽绒棉服外套袄", "goods_image": "//g-search1.alicdn.com/img/bao/uploaded/i4/i2/762822863/O1CN011X1IP1tmgAee5iC_!!0-item_pic.jpg", "goods_detail_url": "https://detail.tmall.com/item.htm?id=540069175433&ns=1&abbucket=8", "goods_product_id": "540069175433", "goods_price": "99.00", "goods_sale_num": 3129, "shop_name": "俞兆林章镇专卖店", "platform": 1, "goods_total_score": "4.9", "goods_comment_num": 3978}, {"goods_cate_name": "连衣裙", "goods_name": "芙娜妮2018秋冬名媛时尚套装裙两件套卫衣长袖格子中长款连衣裙女", "goods_image": "//g-search3.alicdn.com/img/bao/uploaded/i4/i4/736758035/O1CN0129E4rP1pOjUmzzE_!!0-item_pic.jpg", "goods_detail_url": "https://detail.tmall.com/item.htm?id=578063854712&ns=1&abbucket=8", "goods_product_id": "578063854712", "goods_price": "188.00", "goods_sale_num": 2712, "shop_name": "芙娜妮服饰旗舰店", "platform": 1, "goods_total_score": "4.9", "goods_comment_num": 1010}, {"goods_cate_name": "连衣裙", "goods_name": "毛衣配加厚秋冬季套装裙两件2018新款打底背带有女人味的连衣裙子", "goods_image": "//g-search3.alicdn.com/img/bao/uploaded/i4/i2/2956372102/O1CN011ROl0EC6Bq8eOMa_!!2956372102.jpg", "goods_detail_url": "https://detail.tmall.com/item.htm?id=558114277272&ns=1&abbucket=8", "goods_product_id": "558114277272", "goods_price": "198.00", "goods_sale_num": 2712, "shop_name": "吾卉旗舰店", "platform": 1, "goods_total_score": "4.9", "goods_comment_num": 2742}, {"goods_cate_name": "连衣裙", "goods_name": "长款毛衣裙 秋冬2018新款长袖针织连衣裙宽松显瘦毛衣打底裙长裙", "goods_image": "//g-search3.alicdn.com/img/bao/uploaded/i4/i4/2671293231/O1CN011ZjqA90lRrUddJb_!!0-item_pic.jpg", "goods_detail_url": "https://item.taobao.com/item.htm?id=577229801146&ns=1&abbucket=8", "goods_product_id": "577229801146", "goods_price": "89.00", "goods_sale_num": 2712, "shop_name": "小为baby", "platform": 1, "goods_total_score": "4.9", "goods_comment_num": 2930}, {"goods_cate_name": "连衣裙", "goods_name": "秋冬季套装裙女时尚2018秋装新款韩版显瘦气质鹿皮绒两件套连衣裙", "goods_image": "//g-search1.alicdn.com/img/bao/uploaded/i4/i1/3385275239/TB2eFnsrQ7mBKNjSZFyXXbydFXa_!!3385275239-0-item_pic.jpg", "goods_detail_url": "https://detail.tmall.com/item.htm?id=576148683529&ns=1&abbucket=8", "goods_product_id": "576148683529", "goods_price": "168.00", "goods_sale_num": 2712, "shop_name": "洛索亚旗舰店", "platform": 1, "goods_total_score": "4.9", "goods_comment_num": 2128}, {"goods_cate_name": "陶瓷餐具", "goods_name": "碗碟套装 家用欧式简约中式金边组合碗筷景德镇骨瓷餐具套装 碗盘", "goods_image": "//g-search2.alicdn.com/img/bao/uploaded/i4/i1/3284690895/O1CN01RqJgPu1ITwxARo0d8_!!0-item_pic.jpg", "goods_detail_url": "https://detail.tmall.com/item.htm?id=574064597995&ns=1&abbucket=8", "goods_product_id": "574064597995", "goods_price": "398.00", "goods_sale_num": 381, "shop_name": "英伦伍德旗舰店", "platform": 1, "goods_total_score": "4.9", "goods_comment_num": 739}, {"goods_cate_name": "陶瓷餐具", "goods_name": "青花瓷碗套装批发定制会销碗筷青花瓷餐具陶瓷礼品碗套装碗礼盒装", "goods_image": "//g-search3.alicdn.com/img/bao/uploaded/i4/i1/2912386214/TB2CAjaBbBmpuFjSZFAXXaQ0pXa_!!2912386214.jpg", "goods_detail_url": "https://item.taobao.com/item.htm?id=536237260102&ns=1&abbucket=8#detail", "goods_product_id": "536237260102", "goods_price": "3.60", "goods_sale_num": 975, "shop_name": "瓷上功夫0", "platform": 1, "goods_total_score": "4.9", "goods_comment_num": 3579}, {"goods_cate_name": "陶瓷餐具", "goods_name": "简约黑线牛排盘子西餐餐具全套创意牛排刀叉盘子套装陶瓷家用餐盘", "goods_image": "//g-search2.alicdn.com/img/bao/uploaded/i4/i3/2865503059/TB2gjbMxljTBKNjSZFuXXb0HFXa_!!2865503059.jpg", "goods_detail_url": "https://item.taobao.com/item.htm?id=576048776919&ns=1&abbucket=8#detail", "goods_product_id": "576048776919", "goods_price": "38.80", "goods_sale_num": 1278, "shop_name": "匹尔斯", "platform": 1, "goods_total_score": "4.8", "goods_comment_num": 2467}]}
{"info": "操作完成", "code": "200", "data": [{"goods_cate_name": "陶瓷餐具", "goods_name": "墨色 景德镇陶瓷餐具套装美式碗碟套装家用 骨瓷碗盘西式 疏影", "goods_image": "//g-search3.alicdn.com/img/bao/uploaded/i4/i3/1981584175/O1CN011giC2wGWsufkIkb_!!0-item_pic.jpg", "goods_detail_url": "https://detail.tmall.com/item.htm?id=541827522181&ns=1&abbucket=8", "goods_product_id": "541827522181", "goods_price": "369.00", "goods_sale_num": 1069, "shop_name": "墨色家居旗舰店", "platform": 1, "goods_total_score": "4.9", "goods_comment_num": 8623}, {"goods_cate_name": "陶瓷餐具", "goods_name": "火彩碗碟套装家用简约组合中式小清新景德镇骨瓷餐具套装碗盘筷子", "goods_image": "//g-search2.alicdn.com/img/bao/uploaded/i4/i1/2452798435/O1CN012CBHHvkEIS45WYO_!!0-item_pic.jpg", "goods_detail_url": "https://detail.tmall.com/item.htm?id=580675472481&ns=1&abbucket=8", "goods_product_id": "580675472481", "goods_price": "528.00", "goods_sale_num": 409, "shop_name": "火彩家居旗舰店", "platform": 1, "goods_total_score": "4.9", "goods_comment_num": 105}, {"goods_cate_name": "陶瓷餐具", "goods_name": "餐具碗碟套装家用韩式简约景德镇陶瓷碗筷欧式创意组合骨瓷碗盘子", "goods_image": "//g-search1.alicdn.com/img/bao/uploaded/i4/i4/3501529852/O1CN012MeGVmTCSEfodVb_!!3501529852.jpg", "goods_detail_url": "https://item.taobao.com/item.htm?id=571015206032&ns=1&abbucket=8#detail", "goods_product_id": "571015206032", "goods_price": "498.00", "goods_sale_num": 375, "shop_name": "瓷都匠人", "platform": 1, "goods_total_score": "4.8", "goods_comment_num": 3522}, {"goods_cate_name": "陶瓷餐具", "goods_name": "碗碟套装景德镇骨瓷餐具碗盘欧式组合家用珐琅彩陶瓷中式宴请摆台", "goods_image": "//g-search3.alicdn.com/img/bao/uploaded/i4/i4/1056127325/O1CN0123yteT4IYxVYupL_!!0-item_pic.jpg", "goods_detail_url": "https://item.taobao.com/item.htm?id=578458707428&ns=1&abbucket=8#detail", "goods_product_id": "578458707428", "goods_price": "4688.00", "goods_sale_num": 62, "shop_name": "梦秋790222", "platform": 1, "goods_total_score": "4.9", "goods_comment_num": 55}, {"goods_cate_name": "陶瓷餐具", "goods_name": "餐具套装 碗盘家用吃饭北欧ins简约景德镇陶瓷碗碟套装家用2-4人", "goods_image": "//g-search2.alicdn.com/img/bao/uploaded/i4/i2/2453304112/O1CN01PjMTGh1gFL5xEgblV_!!0-item_pic.jpg", "goods_detail_url": "https://detail.tmall.com/item.htm?id=578108964210&ns=1&abbucket=8", "goods_product_id": "578108964210", "goods_price": "39.00", "goods_sale_num": 1100, "shop_name": "恩也旗舰店", "platform": 1, "goods_total_score": "4.9", "goods_comment_num": 692}, {"goods_cate_name": "陶瓷餐具", "goods_name": "餐具套装60头景德镇陶瓷器骨瓷碗盘家用碗碟碗筷碗具结婚乔迁送礼", "goods_image": "//g-search1.alicdn.com/img/bao/uploaded/i4/i1/1857530427/O1CN01qrGFWt1F1bas7Y1Us_!!0-item_pic.jpg", "goods_detail_url": "https://detail.tmall.com/item.htm?id=540805399827&ns=1&abbucket=8", "goods_product_id": "540805399827", "goods_price": "589.00", "goods_sale_num": 471, "shop_name": "爱爵旗舰店", "platform": 1, "goods_total_score": "4.9", "goods_comment_num": 1793}, {"goods_cate_name": "陶瓷餐具", "goods_name": "餐具碗碟套装家用骨瓷欧式简约景德镇陶瓷碗盘子送礼组合中式金边", "goods_image": "//g-search1.alicdn.com/img/bao/uploaded/i4/i3/134068565/O1CN012D8olvZRfCY0BDp_!!134068565.jpg", "goods_detail_url": "https://item.taobao.com/item.htm?id=575000081981&ns=1&abbucket=8#detail", "goods_product_id": "575000081981", "goods_price": "308.00", "goods_sale_num": 623, "shop_name": "梦幻wucheng", "platform": 1, "goods_total_score": "4.9", "goods_comment_num": 2204}, {"goods_cate_name": "陶瓷餐具", "goods_name": "碗家用吃饭碗筷套装餐具礼品碗套装礼盒装小碗具陶瓷碗碟套装家用", "goods_image": "//g-search3.alicdn.com/img/bao/uploaded/i4/i4/1858293206/TB2Gv9Qcr2pK1RjSZFsXXaNlXXa_!!1858293206-0-item_pic.jpg", "goods_detail_url": "https://detail.tmall.com/item.htm?id=552589450434&ns=1&abbucket=8", "goods_product_id": "552589450434", "goods_price": "8.00", "goods_sale_num": 29464, "shop_name": "唐贝旗舰店", "platform": 1, "goods_total_score": "4.8", "goods_comment_num": 99278}, {"goods_cate_name": "陶瓷餐具", "goods_name": "景德镇欧式骨瓷餐具套装组合 中式美式简约描金碗碟盘子家用送礼", "goods_image": "//g-search3.alicdn.com/img/bao/uploaded/i4/i4/2093048082/O1CN01aQtzim29ZbTfY4Rnh_!!0-item_pic.jpg", "goods_detail_url": "https://detail.tmall.com/item.htm?id=573080596523&ns=1&abbucket=8", "goods_product_id": "573080596523", "goods_price": "799.00", "goods_sale_num": 395, "shop_name": "红运达旗舰店", "platform": 1, "goods_total_score": "4.9", "goods_comment_num": 618}, {"goods_cate_name": "陶瓷餐具", "goods_name": "碗碟套装家用景德镇欧式骨瓷餐具碗筷陶瓷器吃饭套碗盘子中式组合", "goods_image": "//g-search2.alicdn.com/img/bao/uploaded/i4/i1/1740350306/O1CN011E8BfLqST0aBX2p_!!0-item_pic.jpg", "goods_detail_url": "https://detail.tmall.com/item.htm?id=521073273597&ns=1&abbucket=8", "goods_product_id": "521073273597", "goods_price": "128.00", "goods_sale_num": 30524, "shop_name": "南极宝泽海专卖店", "platform": 1, "goods_total_score": "4.8", "goods_comment_num": 10674}, {"goods_cate_name": "陶瓷餐具", "goods_name": "简约创意日式餐具2/4/6人碗筷碗碟套装家用碟子吃饭碗盘子陶瓷碗", "goods_image": "//g-search1.alicdn.com/img/bao/uploaded/i4/i4/2865503059/TB2FRvzvkOWBuNjSsppXXXPgpXa_!!2865503059.jpg", "goods_detail_url": "https://item.taobao.com/item.htm?id=567920193177&ns=1&abbucket=8#detail", "goods_product_id": "567920193177", "goods_price": "45.20", "goods_sale_num": 1631, "shop_name": "匹尔斯", "platform": 1, "goods_total_score": "4.8", "goods_comment_num": 13506}]}
{"info": "操作完成", "code": "200", "data": [{"goods_cate_name": "陶瓷餐具", "goods_name": "碗碟套装 景德镇陶瓷器28/56头骨瓷餐具韩式创意家用碗盘餐具套装", "goods_image": "//g-search3.alicdn.com/img/bao/uploaded/i4/i1/1857530427/O1CN011F1banq4SBPLeUE_!!1857530427.png", "goods_detail_url": "https://detail.tmall.com/item.htm?id=521604850016&ns=1&abbucket=8", "goods_product_id": "521604850016", "goods_price": "198.00", "goods_sale_num": 948, "shop_name": "爱爵旗舰店", "platform": 1, "goods_total_score": "4.9", "goods_comment_num": 16554}, {"goods_cate_name": "陶瓷餐具", "goods_name": "碗碟套装 家用欧式金边景德镇餐具套装陶瓷碗盘子碗套装 骨瓷组合", "goods_image": "//g-search2.alicdn.com/img/bao/uploaded/i4/i3/2454241834/O1CN011PQ0rKwE4vfndG4_!!0-item_pic.jpg", "goods_detail_url": "https://detail.tmall.com/item.htm?id=574999466465&ns=1&abbucket=8", "goods_product_id": "574999466465", "goods_price": "408.00", "goods_sale_num": 791, "shop_name": "唐德家居旗舰店", "platform": 1, "goods_total_score": "4.9", "goods_comment_num": 815}, {"goods_cate_name": "陶瓷餐具", "goods_name": "50/80件碗碟套装 家用陶瓷10人吃饭碗盘子菜盘面碗汤碗组合餐具", "goods_image": "//g-search3.alicdn.com/img/bao/uploaded/i4/i4/2883582525/O1CN011UWUWo7JlCBQf0q_!!2883582525.jpg", "goods_detail_url": "https://item.taobao.com/item.htm?id=574972647896&ns=1&abbucket=8#detail", "goods_product_id": "574972647896", "goods_price": "49.00", "goods_sale_num": 4150, "shop_name": "启依餐具", "platform": 1, "goods_total_score": "4.9", "goods_comment_num": 9935}, {"goods_cate_name": "陶瓷餐具", "goods_name": "特价10人用碗 高档瓷家用54头碗碟套装 中式盘子碗筷组合简约餐具", "goods_image": "//g-search3.alicdn.com/img/bao/uploaded/i4/i4/2909469689/O1CN012LRbwZHOaaathV7_!!2909469689.jpg", "goods_detail_url": "https://item.taobao.com/item.htm?id=578581639221&ns=1&abbucket=8#detail", "goods_product_id": "578581639221", "goods_price": "128.00", "goods_sale_num": 2009, "shop_name": "金麒麟陶瓷馆", "platform": 1, "goods_total_score": "4.8", "goods_comment_num": 1071}, {"goods_cate_name": "陶瓷餐具", "goods_name": "碗碟套装 家用骨瓷餐具套装景德镇陶瓷瓷器70头高档欧式碗盘组合", "goods_image": "//g-search2.alicdn.com/img/bao/uploaded/i4/i1/1689543190/O1CN01nSAiZy1ZR3vEpy8Qv_!!0-item_pic.jpg", "goods_detail_url": "https://detail.tmall.com/item.htm?id=525536951146&ns=1&abbucket=8", "goods_product_id": "525536951146", "goods_price": "779.00", "goods_sale_num": 393, "shop_name": "远业陶瓷旗舰店", "platform": 1, "goods_total_score": "4.9", "goods_comment_num": 3299}, {"goods_cate_name": "陶瓷餐具", "goods_name": "碗碟套装 家用欧式景德镇高档骨瓷金边碗盘餐具套装 碗筷组合送礼", "goods_image": "//g-search3.alicdn.com/img/bao/uploaded/i4/i3/1756892659/O1CN011VVrc4EQDT3lllq_!!1756892659.jpg", "goods_detail_url": "https://item.taobao.com/item.htm?id=575461078506&ns=1&abbucket=8#detail", "goods_product_id": "575461078506", "goods_price": "408.00", "goods_sale_num": 943, "shop_name": "金丝陶瓷", "platform": 1, "goods_total_score": "4.8", "goods_comment_num": 1212}, {"goods_cate_name": "陶瓷餐具", "goods_name": "橙叶骨瓷餐具碗碟套装家用欧式景德镇陶瓷器中式碗盘筷子组合简约", "goods_image": "//g-search3.alicdn.com/img/bao/uploaded/i4/i1/745858104/O1CN0129jgBn0SXFCNpa6_!!0-item_pic.jpg", "goods_detail_url": "https://detail.tmall.com/item.htm?id=565599051927&ns=1&abbucket=8", "goods_product_id": "565599051927", "goods_price": "398.00", "goods_sale_num": 1022, "shop_name": "橙叶家居旗舰店", "platform": 1, "goods_total_score": "4.9", "goods_comment_num": 4983}, {"goods_cate_name": "陶瓷餐具", "goods_name": "碗碟套装 家用简约骨瓷欧式碗筷组合景德镇中式套碗餐具套装 碗盘", "goods_image": "//g-search1.alicdn.com/img/bao/uploaded/i4/i1/2036929907/O1CN012N3SIX8pqvehy7O_!!0-item_pic.jpg", "goods_detail_url": "https://detail.tmall.com/item.htm?id=571604775656&ns=1&abbucket=8", "goods_product_id": "571604775656", "goods_price": "399.00", "goods_sale_num": 897, "shop_name": "韵之和旗舰店", "platform": 1, "goods_total_score": "4.9", "goods_comment_num": 2020}, {"goods_cate_name": "陶瓷餐具", "goods_name": "中式碗碟套装家用骨瓷餐具组合盘子景德镇欧式简约陶瓷吃饭碗筷", "goods_image": "//g-search3.alicdn.com/img/bao/uploaded/i4/i3/2093048082/O1CN01QZc76S29ZbTfhyqtZ_!!0-item_pic.jpg", "goods_detail_url": "https://detail.tmall.com/item.htm?id=543477245688&ns=1&abbucket=8", "goods_product_id": "543477245688", "goods_price": "469.00", "goods_sale_num": 730, "shop_name": "红运达旗舰店", "platform": 1, "goods_total_score": "4.9", "goods_comment_num": 6420}, {"goods_cate_name": "陶瓷餐具", "goods_name": "骨瓷餐具碗碟套装 家用组合欧式陶瓷碗筷景德镇简约中式盘子 玉清", "goods_image": "//g-search3.alicdn.com/img/bao/uploaded/i4/i3/1981584175/O1CN01mdVwli1giC2wqI8Zw_!!0-item_pic.jpg", "goods_detail_url": "https://detail.tmall.com/item.htm?id=544856464033&ns=1&abbucket=8", "goods_product_id": "544856464033", "goods_price": "389.00", "goods_sale_num": 741, "shop_name": "墨色家居旗舰店", "platform": 1, "goods_total_score": "4.9", "goods_comment_num": 10675}, {"goods_cate_name": "陶瓷餐具", "goods_name": "碗碟套装家用4人欧式简约陶瓷碗筷盘子组合日式北欧ins餐具吃饭碗", "goods_image": "//g-search3.alicdn.com/img/bao/uploaded/i4/i3/1688729419/TB1RKJIzhWYBuNjy1zkXXXGGpXa_!!0-item_pic.jpg", "goods_detail_url": "https://detail.tmall.com/item.htm?id=566210181110&ns=1&abbucket=8", "goods_product_id": "566210181110", "goods_price": "79.00", "goods_sale_num": 2344, "shop_name": "wuxin家居旗舰店", "platform": 1, "goods_total_score": "4.9", "goods_comment_num": 6040}]}
